CHANGELOG
LICENSE
MANIFEST.in
README.md
__init__.py
setup.cfg
setup.py
test-new-relic-api.py
test.py
test2.py
Portfolio_py.egg-info/PKG-INFO
Portfolio_py.egg-info/SOURCES.txt
Portfolio_py.egg-info/dependency_links.txt
Portfolio_py.egg-info/entry_points.txt
Portfolio_py.egg-info/not-zip-safe
Portfolio_py.egg-info/pbr.json
Portfolio_py.egg-info/requires.txt
Portfolio_py.egg-info/top_level.txt
devtest/__init__.py
devtest/manage.py
devtest/run_boom.py
devtest/run_hello.py
devtest/run_www.py
devtest/application/__init__.py
devtest/application/config.py
devtest/application/model.py
devtest/application/test.py
devtest/application/boom/__init__.py
devtest/application/boom/views.py
devtest/application/hello/__init__.py
devtest/application/hello/views.py
devtest/application/www/__init__.py
devtest/application/www/views.py
portfolio/__init__.py
portfolio/cmd.py
portfolio/pkginfo.py
portfolio/utils.py
portfolio/app_templates/__init__.py
portfolio/app_templates/config.py
portfolio/app_templates/init.py
portfolio/app_templates/manage.py
portfolio/app_templates/model.py
portfolio/app_templates/run.py
portfolio/app_templates/admin/__init__.py
portfolio/app_templates/admin/views.py
portfolio/app_templates/default/__init__.py
portfolio/app_templates/default/views.py
portfolio/component/__init__.py
portfolio/component/model.py
portfolio/component/views/__init__.py
portfolio/component/views/contact_page.py
portfolio/component/views/error_page.py
portfolio/component/views/maintenance_page.py
portfolio/component/views/post_admin.py
portfolio/component/views/post_reader.py
portfolio/component/views/user_account.py
portfolio/component/views/user_admin.py
tests/__init__.py
tests/test_component.py
tests/test_pylot.py
tests/test_utils.py